setup.cfg
setup.py
DtwSom.egg-info/PKG-INFO
DtwSom.egg-info/SOURCES.txt
DtwSom.egg-info/dependency_links.txt
DtwSom.egg-info/requires.txt
DtwSom.egg-info/top_level.txt
dtwsom/__init__.py
dtwsom/dtwsom.py