Metadata-Version: 2.1
Name: DtwSom
Version: 1.0
Summary: Implementation of the Dynamic Time Warping Self Organizing Maps (DTW-SOM)
Home-page: https://github.com/Kenan-Li/dtwsom
Author: Kenan Li
Author-email: kenanl@usc.edu
License: CC BY 3.0
Download-URL: https://github.com/Kenan-Li/dtwsom/archive/master.zip
Keywords: self-organizing map,time series analysis,clustering,dimentionality reduction,dynamic time warping
Platform: UNKNOWN
